mymodule.py
pypoetrylib-0.5.0.dist-info/LICENSE
pypoetrylib-0.5.0.dist-info/WHEEL
pypoetrylib-0.5.0.dist-info/METADATA
pypoetrylib-0.5.0.dist-info/RECORD
